sqlalchemy_extended/__init__.py
sqlalchemy_extended/base_model.py
sqlalchemy_extended-0.1.1.dist-info/AUTHORS.rst
sqlalchemy_extended-0.1.1.dist-info/LICENSE
sqlalchemy_extended-0.1.1.dist-info/METADATA
sqlalchemy_extended-0.1.1.dist-info/WHEEL
sqlalchemy_extended-0.1.1.dist-info/top_level.txt
sqlalchemy_extended-0.1.1.dist-info/RECORD
