Metadata-Version: 2.1
Name: sqlalchemy-extended
Version: 0.1.1
Summary: Extensions to SQLALchemy
Home-page: https://github.com/kartstig/sqlalchemy_extended
Author: Herman Singh
Author-email: kartstig@gmail.com
License: MIT license
Keywords: sqlalchemy_extended
Platform: UNKNOWN
Classifier: Development Status :: 2 - Pre-Alpha
Classifier: Intended Audience :: Developers
Classifier: License :: OSI Approved :: MIT License
Classifier: Natural Language :: English
Classifier: Programming Language :: Python :: 3
Classifier: Programming Language :: Python :: 3.6
Classifier: Programming Language :: Python :: 3.7
Classifier: Programming Language :: Python :: 3.8
Requires-Python: >=3.6
Requires-Dist: SQLAlchemy (>=1)
